st_mui_multiselect/__init__.py
st_mui_multiselect/frontend/.env
st_mui_multiselect/frontend/.prettierrc
st_mui_multiselect/frontend/build/asset-manifest.json
st_mui_multiselect/frontend/build/bootstrap.min.css
st_mui_multiselect/frontend/build/bootstrap.min.css.map
st_mui_multiselect/frontend/build/index.html
st_mui_multiselect/frontend/build/precache-manifest.df06a68db74a8918b5034c1ed5f7d978.js
st_mui_multiselect/frontend/build/service-worker.js
st_mui_multiselect/frontend/build/static/js/2.32345768.chunk.js
st_mui_multiselect/frontend/build/static/js/2.32345768.chunk.js.LICENSE.txt
st_mui_multiselect/frontend/build/static/js/2.32345768.chunk.js.map
st_mui_multiselect/frontend/build/static/js/main.1e2484a6.chunk.js
st_mui_multiselect/frontend/build/static/js/main.1e2484a6.chunk.js.map
st_mui_multiselect/frontend/build/static/js/runtime-main.25638943.js
st_mui_multiselect/frontend/build/static/js/runtime-main.25638943.js.map
st_mui_multiselect/frontend/package-lock.json
st_mui_multiselect/frontend/package.json
st_mui_multiselect/frontend/public/bootstrap.min.css
st_mui_multiselect/frontend/public/bootstrap.min.css.map
st_mui_multiselect/frontend/public/index.html
st_mui_multiselect/frontend/src/StMuiMultiselect.tsx
st_mui_multiselect/frontend/src/index.tsx
st_mui_multiselect/frontend/src/react-app-env.d.ts
st_mui_multiselect/frontend/tsconfig.json
st_mui_multiselect-0.1.3.dist-info/LICENSE
st_mui_multiselect-0.1.3.dist-info/WHEEL
st_mui_multiselect-0.1.3.dist-info/METADATA
st_mui_multiselect-0.1.3.dist-info/RECORD
