Metadata-Version: 2.1
Name: st-mui-multiselect
Version: 0.1.3
Summary: Multiselect component for Streamlit using Material UI's tool
Home-page: https://github.com/supern8ent/st-mui-multiselect
Keywords: streamlit
Author: Nathan Lloyd
Author-email: nat272@gmail.com
Requires-Python: >=3.8, !=2.7.*, !=3.0.*, !=3.1.*, !=3.2.*, !=3.3.*, !=3.4.*, !=3.5.*, !=3.6.*, !=3.7.*
Classifier: Programming Language :: Python :: 3
Classifier: Programming Language :: Python :: 3.10
Classifier: Programming Language :: Python :: 3.9
Requires-Dist: streamlit (>=1.12.2,<2.0.0)
Project-URL: Repository, https://github.com/supern8ent/st-mui-multiselect
